athlete/__init__.py
athlete/agent.py
athlete/constants.py
athlete/function.py
athlete/global_objects.py
athlete/algorithms/__init__.py
athlete/algorithms/registry.py
athlete/algorithms/ddpg/__init__.py
athlete/algorithms/ddpg/policy.py
athlete/algorithms/ddpg/updatable_components.py
athlete/algorithms/ddpg/update.py
athlete/algorithms/dqn/__init__.py
athlete/algorithms/dqn/policy.py
athlete/algorithms/dqn/updatable_components.py
athlete/algorithms/dqn/update.py
athlete/algorithms/ppo/__init__.py
athlete/algorithms/ppo/module.py
athlete/algorithms/ppo/policy.py
athlete/algorithms/ppo/updatable_components.py
athlete/algorithms/ppo/update.py
athlete/algorithms/q_learning/__init__.py
athlete/algorithms/q_learning/policy.py
athlete/algorithms/q_learning/updatable_components.py
athlete/algorithms/q_learning/update.py
athlete/algorithms/sac/__init__.py
athlete/algorithms/sac/module.py
athlete/algorithms/sac/policy.py
athlete/algorithms/sac/updatable_components.py
athlete/algorithms/sac/update.py
athlete/algorithms/td3/__init__.py
athlete/algorithms/td3/updatable_components.py
athlete/algorithms/td3/update.py
athlete/data_collection/__init__.py
athlete/data_collection/collector.py
athlete/data_collection/on_policy.py
athlete/data_collection/provider.py
athlete/data_collection/transition.py
athlete/module/torch/__init__.py
athlete/module/torch/common.py
athlete/module/torch/fully_connected.py
athlete/policy/__init__.py
athlete/policy/noise.py
athlete/policy/policy.py
athlete/saving/__init__.py
athlete/saving/file_handler.py
athlete/saving/saveable_component.py
athlete/update/__init__.py
athlete/update/buffer.py
athlete/update/buffer_wrapper.py
athlete/update/common.py
athlete/update/on_policy_buffer.py
athlete/update/update_rule.py
rl_athlete-0.2.0.dist-info/licenses/LICENSE
rl_athlete-0.2.0.dist-info/METADATA
rl_athlete-0.2.0.dist-info/WHEEL
rl_athlete-0.2.0.dist-info/top_level.txt
rl_athlete-0.2.0.dist-info/RECORD
