Metadata-Version: 2.4
Name: rl-athlete
Version: 0.2.0
Summary: An API for reinforcement learning agents.
Author-email: Sebastian Griesbach <sebastian.griesbach@zoho.eu>
License: MIT License
Project-URL: Homepage, https://github.com/Sebastian-Griesbach/athlete
Project-URL: Repository, https://github.com/Sebastian-Griesbach/athlete
Classifier: Programming Language :: Python :: 3
Classifier: License :: OSI Approved :: MIT License
Classifier: Operating System :: OS Independent
Requires-Python: >=3.9
License-File: LICENSE
Requires-Dist: numpy
Requires-Dist: cpprb
Requires-Dist: gymnasium[classic-control]
Requires-Dist: torch>=2.0.0
Dynamic: license-file
